[{"paperID": "2358", "keywords": ["explore", "interactive", "dashboard", "interface", "visualization", "medical", "algorithm", "bioinformatics"]}, {"paperID": "2369", "keywords": ["clinical", "decision support", "machine learning", "clinical", "clinical", "clinical", "interface", "automated", "clinicians", "clinically", "clinical", "clinical", "medical", "interface", "machine learning", "clinical", "decision support", "clinician", "clinicians", "clinical", "interface", "clinical", "automated", "medical", "clinical", "clinical", "decision support", "clinical", "medical", "interaction", "medical", "decision support", "medical", "interaction", "machine learning"]}, {"paperID": "2372", "keywords": ["interactive", "explore", "health", "machine learning", "visualization", "interactive", "interactive", "interactive", "healthy", "interactive", "healthy", "interactive", "visualization", "medical", "health", "machine learning", "health", "machine learning"]}, {"paperID": "2378", "keywords": ["big data", "interactive", "visualization", "big data", "big data", "interactive", "visualization", "big data", "visualization", "big data", "interactions", "health", "big data", "analytics", "visualization", "big data", "interactive", "visualization", "big data", "big data", "analytics", "big data", "health", "interactive", "visualization", "analytics", "big data", "analytics", "visualization", "analytics", "visualization"]}, {"paperID": "2379", "keywords": ["clinical", "health", "health", "electronic health record", "health", "interactive", "visual", "clinicians", "predict", "clinical", "predictive", "analytics", "medical", "clinical", "decision support", "clinical", "electronic health records", "predictive", "analytics", "healthcare"]}, {"paperID": "2382", "keywords": ["explore", "interactive", "dashboard", "interface", "visualization", "medical", "algorithm", "bioinformatics"]}, {"paperID": "2386", "keywords": ["interactive", "clinical", "biomedical", "automated", "clinical", "medicine", "visualization", "interactive", "machine learning", "visualization", "clinical", "biomedical", "algorithm", "clinical", "algorithm", "clinical", "decision support", "visualization", "clinical", "biomedical", "medical", "clinical", "interactive", "interface", "algorithm", "clinical", "decision support", "machine learning", "algorithm"]}, {"paperID": "2387", "keywords": ["clinical", "decision support", "health", "clinical", "medical", "clinical", "algorithm", "medications", "medication", "interaction", "clinical", "interactions", "clinicians", "medical", "medical", "medical", "visualization", "interactions", "medication", "medication", "medications", "clinical", "decision support", "clinical", "interaction"]}, {"paperID": "2392", "keywords": ["deep learning", "visual", "analytics", "electronic health records", "electronic health record", "deep learning", "visualization", "medical", "interactive", "visually", "predict", "clinical", "deep learning", "exploratory", "medical", "explore", "clinical", "big data", "medical", "deep learning", "electronic health records", "visual", "analytics", "health", "visualization"]}, {"paperID": "2393", "keywords": ["predictions", "prediction", "clinical", "prediction", "prediction", "graphical", "interface", "predictions", "prediction", "prediction", "prediction", "prediction", "prediction", "exploration", "clinical", "prediction", "medical", "prediction"]}, {"paperID": "2395", "keywords": ["clinical", "health", "health", "algorithms", "decision support", "decision support", "interaction", "interact", "interaction", "machine learning", "clinical", "visualization", "interaction", "clinical"]}, {"paperID": "2397", "keywords": ["visual", "analytics", "healthcare", "health", "health", "interactive", "visual", "analytics", "interactive", "interface", "exploration", "interactive", "machine learning", "health", "health", "visual", "analytics", "health", "visualization", "health", "interactive", "interactive", "machine learning", "visual", "analytics"]}, {"paperID": "2404", "keywords": ["interactive", "clinical", "interactive", "clinical", "clinical", "visualization", "clinical", "interactive", "visualization", "clinical", "clinical", "visualizing", "clinical", "clinicians", "predict", "clinicians", "interactive", "prediction", "visualization", "visualizing", "clinical", "clinical", "data mining", "medical", "clinical", "clinical"]}, {"paperID": "2405", "keywords": ["interactive", "visual", "exploration", "healthy", "visualization", "visual", "exploration", "interactive", "visual", "visual", "visualization", "data mining", "visualization", "visualization", "healthy", "visual", "visual", "exploration", "visualization"]}, {"paperID": "2406", "keywords": ["interactive", "visualization", "automated", "machine learning", "clinicians", "clinical", "visualization", "clinics", "machine learning"]}, {"paperID": "2411", "keywords": ["visual", "clinical", "decision support", "clinical", "decision support", "clinical", "clinical", "interactive", "clinical", "decision support", "visual", "clinical", "clinical", "medical", "decision support", "medical", "artificial intelligence", "clinical", "clinical", "decision support", "clinical", "decision support", "clinical", "clinical", "decision support"]}, {"paperID": "2419", "keywords": ["visualization", "prediction", "data mining", "health", "explore", "exploratory", "visualized", "explored", "data mining", "algorithms", "prediction", "artificial intelligence", "visualization", "health", "data mining", "algorithm", "exploratory", "health", "prediction", "data mining"]}, {"paperID": "2420", "keywords": ["visualization", "visualization", "exploring", "medical", "visualization", "interactive", "visualization", "visualization", "medical", "algorithm", "health", "health", "algorithms", "visualization", "health"]}, {"paperID": "2421", "keywords": ["interactive", "prediction", "visualization", "explore", "bioinformatics", "machine learning", "medical", "bioinformatics", "visualization", "machine learning"]}, {"paperID": "2422", "keywords": ["medical", "deep learning", "electronic health records", "visual", "analytics", "deep learning", "health", "deep learning", "medical", "clinicians", "medical", "visual", "exploration", "interaction", "electronic health record", "clinicians", "exploring", "prediction", "interactive", "clinical", "prediction", "exploration", "predict", "clinical", "medical", "medical", "medical", "clinical", "medical", "clinical", "exploration", "prediction", "medical", "explore", "prediction", "interactive", "clinical", "prediction", "deep learning", "visual", "analytics", "predict", "clinical", "visually", "prediction", "prediction", "interactive", "clinical", "predictions", "medical", "electronic health records", "deep learning", "visual", "analytics"]}, {"paperID": "2424", "keywords": ["medical", "deep learning", "electronic health records", "visual", "analytics", "deep learning", "health", "deep learning", "medical", "clinicians", "medical", "visual", "exploration", "interaction", "electronic health record", "clinicians", "exploring", "prediction", "interactive", "clinical", "prediction", "exploration", "predict", "clinical", "medical", "medical", "medical", "clinical", "medical", "clinical", "exploration", "prediction", "medical", "explore", "prediction", "interactive", "clinical", "prediction", "deep learning", "visual", "analytics", "predict", "clinical", "visually", "prediction", "prediction", "interactive", "clinical", "predictions", "medical", "electronic health records", "deep learning", "visual", "analytics"]}, {"paperID": "2430", "keywords": ["artificial intelligence", "analytics", "machine learning", "artificial intelligence", "prediction", "predict", "medical", "machine learning", "artificial intelligence", "machine learning", "interactive", "dashboard", "machine learning", "analytics", "machine learning", "prediction", "medical", "artificial intelligence", "machine learning", "prediction"]}, {"paperID": "2440", "keywords": ["visual", "analytics", "electronic health records", "electronic health record", "machine learning", "visual", "analytics", "visual", "analytics", "electronic health records", "interactive", "visualizations", "healthcare", "electronic health records", "interaction", "interactive", "visualization", "visual", "analytics"]}, {"paperID": "2442", "keywords": ["visual", "analytics", "medical", "machine learning", "medicine", "healthcare", "clinicians", "medical", "medical", "visual", "analytics", "interactive", "interface", "medical", "visual", "analytics"]}, {"paperID": "2443", "keywords": ["machine learning", "visualizations", "machine learning", "medicine", "bioinformatics", "visualization", "visualization", "interactive", "visualization", "visualization", "interactive", "exploring", "interactive", "visualization", "visualization", "graphics", "machine learning", "machine learning", "machine learning", "visualization", "visualization", "visual", "analytics", "visualization", "machine learning", "machine learning", "machine learning", "machine learning", "visualization", "machine learning", "interactive", "visualizations", "machine learning", "visualization", "visualization", "visualization"]}, {"paperID": "2456", "keywords": ["interactive", "graphical", "interface", "medical", "graphical", "interface", "medicine", "analytics", "visualization", "interface", "medicine", "interactive", "interactive", "prediction", "medical", "medical", "interactive", "visualization", "medical", "analytics", "analytics", "graphical", "medicine", "visualization", "interface", "graphical", "interactive", "graphical", "interface", "medical", "interface", "interface"]}, {"paperID": "2459", "keywords": ["visual", "exploratory", "health", "predicting", "health", "health", "exploratory", "visualizations", "visualization", "medical", "visualization", "clinical", "medical", "visual", "exploratory", "algorithm", "health", "graphics", "health", "algorithms", "graphics", "health", "health"]}, {"paperID": "2460", "keywords": ["predicting", "medical", "medical", "predicting", "clinical", "graphic", "interface", "exploratory", "predictive", "analytics", "clinical", "graphic", "interface", "medical", "medical"]}, {"paperID": "2463", "keywords": ["visualizing", "visualized", "visual", "analytics", "interactively", "visualize", "algorithm", "automated", "interactively", "clinical"]}, {"paperID": "2470", "keywords": ["exploratory", "exploratory", "visually", "medical", "healthcare", "visualization", "prediction", "predicting", "graphical", "visual", "visualization", "predict", "exploratory", "visualization", "visualization", "exploratory", "graphical", "health", "visualization", "visualization"]}, {"paperID": "2471", "keywords": ["visual", "analytics", "interactive", "visualization", "clinical", "analytics", "exploratory", "visualization", "automated", "visualization", "interface", "medicine", "medical", "graphics", "graphics"]}, {"paperID": "2474", "keywords": ["interactive", "medicine", "interactions", "clinical", "data mining", "algorithms", "biomedical", "automated", "graphical", "interactive", "visualization", "exploratory", "biomedical", "medical", "graphics", "graphics"]}, {"paperID": "2478", "keywords": ["visually", "machine learning", "algorithms", "interact", "interactive", "interface", "decision support", "interactions", "medically", "interface", "interface", "interface", "decision support", "machine learning", "medical", "clinical", "decision support", "machine learning"]}, {"paperID": "2479", "keywords": ["visual", "analytics", "medical", "medical", "prediction", "interactive", "visual", "exploration", "visual", "analytics", "clinical", "visualization", "interactive", "clinical", "interactive", "interactive", "medical", "visual", "clinician", "graphical", "visual", "visual", "analytics", "medical", "clinical", "clinical", "medical", "medical", "visual"]}, {"paperID": "2481", "keywords": ["explorer", "machine learning", "clinical", "machine learning", "explorer", "clinical", "graphical", "interface", "visually", "clinical", "visualization", "medical", "machine learning", "medical", "clinical", "visualization", "clinical", "machine learning", "machine learning", "machine learning", "explorer"]}, {"paperID": "2482", "keywords": ["interactive", "bioinformatics", "interface", "interactive", "visualization", "bioinformatics", "interface", "interactive", "visualization", "interactive", "graphic", "big data", "bioinformatics", "medical", "big data", "visualization"]}, {"paperID": "2483", "keywords": ["electronic health record", "artificial intelligence", "clinical", "health", "artificial intelligence", "algorithm", "electronic health record", "clinical", "explores", "medical", "clinical", "health", "health", "electronic health record", "health", "dashboard", "health", "electronic health record", "interface", "clinical", "health", "health", "health", "artificial intelligence", "health", "artificial intelligence", "artificial intelligence", "algorithms", "artificial intelligence", "electronic health record", "electronic health record", "interface", "health"]}, {"paperID": "2484", "keywords": ["electronic health records", "health", "medicine", "electronic health records", "machine learning", "biomedical", "explore", "exploration", "exploration", "biomedical", "interface", "electronic health records", "visual", "analytics", "medical", "electronic health record", "medical", "medical"]}, {"paperID": "2485", "keywords": ["automated", "explored", "graphical", "interface", "biomedical", "graphical", "interface", "graphical", "medical", "biomedical", "medical", "algorithm", "interface", "algorithms", "interface"]}, {"paperID": "2494", "keywords": ["machine learning", "healthcare", "machine learning", "machine learning", "decision support", "machine learning", "algorithms", "interactive", "interface", "machine learning", "automated", "machine learning", "healthcare", "decision support", "interface", "algorithms", "health", "machine learning"]}, {"paperID": "2505", "keywords": ["prediction", "big data", "predictive", "clinical", "interactive", "clinical", "decision support", "interface", "prediction", "clinical", "medical", "medical", "predictive", "clinical", "interface", "clinical", "health", "clinical", "decision support", "interface", "clinical", "clinicians", "clinicians", "clinical", "decision support", "prediction"]}, {"paperID": "2506", "keywords": ["visual", "analytics", "clinical", "health", "health", "algorithms", "medical", "clinically", "clinical", "visualization", "interactive", "visualizations", "visually", "interactively", "exploring", "clinically", "visualization", "visualization", "clinical", "interactive", "visualizations", "health"]}, {"paperID": "2510", "keywords": ["visual", "visual", "analytics", "visualization", "visual", "analytics", "interactively", "visualized", "explore", "algorithm", "interactively", "visualization", "algorithm", "interactive", "exploration", "medical", "medical", "visualization", "visual", "analytics", "medical", "exploration", "visual", "analytics", "visualization", "visualization", "medical"]}, {"paperID": "2511", "keywords": ["interactive", "exploratory", "prediction", "machine learning", "predictive", "machine learning", "visualizing", "visualizations", "visualizes", "interactively", "visualization", "interactively", "visualization", "medical", "decision support", "prediction", "machine learning", "prediction", "data mining", "visualization", "decision support", "health", "visualization", "exploratory", "machine learning", "prediction", "predictive", "machine learning"]}, {"paperID": "2512", "keywords": ["clinical", "health", "health", "machine learning", "visual", "analytics", "interactive", "machine learning", "visual", "data mining", "clinical", "data mining", "machine learning", "interactive", "machine learning"]}, {"paperID": "2521", "keywords": ["predictive", "analytics", "biomedical", "clinical", "medical", "medical", "health", "electronic health records", "medical", "medical", "interactive", "dashboard", "medical", "prediction", "machine learning", "medical", "medicines", "electronic health record", "predictive", "clinical", "electronic health record", "machine learning", "medical", "predictive", "analytics"]}, {"paperID": "2523", "keywords": ["visual", "analytics", "medical", "visual", "analytics", "decision support", "visualization", "data mining", "data mining", "visual", "analytics", "explore", "visually", "interacting", "visual", "analytics", "visualization", "visual", "medical", "data mining", "decision support", "visual", "analytics", "analytics", "artificial intelligence", "visualization", "decision support", "visualization", "data mining", "decision support", "visualization", "visual", "analytics", "data mining"]}, {"paperID": "2529", "keywords": ["visual", "analytics", "exploring", "visualizations", "visualize", "electronic health record", "visual", "analytics", "visualized", "visualization", "exploratory", "visual", "analytics", "medical", "visualization", "visual", "visualizations", "visualization", "medical", "visual", "analytics", "visualization", "medical", "visual", "analytics", "algorithms", "visualization", "medical", "electronic health record", "visual", "analytics", "visual", "analytics", "visualization", "medical", "electronic health record"]}, {"paperID": "2531", "keywords": ["healthcare", "analytics", "healthcare", "medical", "healthcare", "medicine", "interactions", "healthcare", "clinical", "healthcare", "big data", "medical", "health", "big data", "visualization", "clinical", "health", "healthcare", "healthcare", "medical", "medications", "health", "healthcare", "big data", "healthcare", "visualization"]}, {"paperID": "2534", "keywords": ["electronic health records", "interactive", "visualization", "electronic health records", "interactive", "visualization", "clinical", "visualization", "predicting", "predicting", "electronic health records", "interactive", "visualizations", "visualization"]}, {"paperID": "2537", "keywords": ["visual", "health", "electronic health records", "health", "visual", "clinical", "health", "electronic health records", "healthy", "healthy", "clinical", "health", "explore", "clinical", "visual", "clinical", "visualization", "electronic health records", "machine learning", "algorithms", "clinical", "electronic health record"]}, {"paperID": "2542", "keywords": ["visualization", "clinical", "interactive", "graphical", "interface", "visualize", "clinical", "medical", "algorithm", "machine learning", "prediction"]}, {"paperID": "2550", "keywords": ["visualization", "interface", "interactions", "prediction", "interface", "interactive", "visually", "explore", "visual", "interactions", "visual", "analytics", "visualize", "interface", "interactions", "data mining", "graphics", "visualization", "interactive", "interactions", "visual", "analytics", "medical", "clinical", "interface", "interactions", "interface"]}, {"paperID": "2552", "keywords": ["electronic health records", "interactive", "visualization", "electronic health records", "interactive", "visualization", "clinical", "visualization", "predicting", "predicting", "electronic health records", "interactive", "visualizations", "visualization"]}, {"paperID": "2553", "keywords": ["interface", "decision support", "predict", "interactions", "clinical", "healthcare", "medical", "decision support", "clinical", "interaction"]}, {"paperID": "2554", "keywords": ["prediction", "predictors", "clinical", "predictive", "predictive", "predicting", "explore", "interface", "predictability", "explore", "medical", "prediction", "predictive"]}, {"paperID": "2556", "keywords": ["visual", "analytics", "visual", "analytics", "health", "clinical", "visualization", "predictive", "interactive", "visualization", "interactive", "visualization", "graphic", "clinical"]}, {"paperID": "2557", "keywords": ["clinical", "medicine", "bioinformatics", "interface", "interactive", "clinical", "predictive", "medical", "clinical", "clinical", "medical", "predictive"]}, {"paperID": "2558", "keywords": ["visualizations", "visualization", "health", "healthy", "health", "interactive", "visualizations", "visualizations", "prediction", "visualizations", "visualization", "visual", "analytics", "health", "visual", "medical", "health", "healthy", "clinical", "prediction", "health", "health"]}, {"paperID": "2559", "keywords": ["interface", "predicting", "automated", "bioinformatics", "graphical", "interface", "algorithm", "explored", "predict", "graphical", "interface", "graphical", "graphical"]}, {"paperID": "2560", "keywords": ["electronic health records", "automated", "clinically", "electronic health records", "clinical", "clinical", "clinical", "clinical", "clinicians", "visual", "algorithm", "interactive", "visualizations", "health", "automated", "clinicians", "clinical", "clinical", "decision support", "electronic health records", "health", "medical", "algorithm", "electronic health record", "algorithms", "electronic health records"]}, {"paperID": "2567", "keywords": ["visual", "analytics", "bioinformatics", "interactive", "visual", "visual", "exploration", "interactive", "medical", "algorithm", "algorithms"]}, {"paperID": "2568", "keywords": ["exploration", "machine learning", "healthcare", "exploring", "healthcare", "health", "exploratory", "interface", "analytics", "interface", "exploration", "clinical", "interactive", "visualization", "interface", "health", "exploratory", "interactive", "visualization"]}, {"paperID": "2571", "keywords": ["visual", "exploration", "visual", "exploration", "biomedical", "healthcare", "visual", "analytics", "visualizes", "explore", "visual", "visual", "visualization", "health", "visual", "analytics", "visual", "exploration", "medical", "machine learning", "machine learning"]}, {"paperID": "2573", "keywords": ["health", "interactive", "healthcare", "visualisation", "health", "health", "visualisation", "analytics", "decision support", "visualisation", "medical", "healthcare", "medical", "clinical", "electronic health records", "analytics", "data mining", "decision support", "visualisation", "visualisation", "visualisation", "interact", "visualisation", "visualisation", "visualisation", "clinical", "clinical", "healthcare", "visual", "analytics", "visualisation", "artificial intelligence", "bioinformatics", "analytics", "data mining", "visualization", "decision support", "health", "visualization", "electronic health record", "healthcare", "visual", "analytics", "medical"]}, {"paperID": "2575", "keywords": ["visual", "medical", "clinical", "visual", "data mining", "visual", "predicting", "visualization", "algorithm", "visual", "visual", "visualization", "interactively", "visualization", "algorithm", "interactions", "visual", "visualization", "prediction", "visual", "analytics", "visual", "data mining", "algorithms", "analytics", "data mining", "visualization", "algorithms", "visualization", "predictions", "visual", "data mining", "visualization", "visualization"]}, {"paperID": "2581", "keywords": ["medical", "visualize", "visualization", "interactive", "visualization", "algorithm", "visualisation", "visualization", "visualisation", "visualisation", "interactive", "visualisation", "medicines", "visualization", "visualisation", "interactive", "visualisation", "medicines", "visualization"]}, {"paperID": "2583", "keywords": ["visual", "interactive", "algorithms", "predictions", "predictions", "visual", "visualization", "visualization", "interactivity", "decision support", "artificial intelligence", "medical", "decision support", "visualization", "bioinformatics", "decision support", "algorithms", "machine learning", "visualization", "interactivity", "medical", "visual"]}, {"paperID": "2590", "keywords": ["visual", "analytics", "bioinformatics", "interactive", "visual", "visual", "exploration", "interactive", "medical", "algorithm", "algorithms"]}, {"paperID": "2595", "keywords": ["interactive", "interface", "clinical", "artificial intelligence", "deep learning", "interface", "predictions", "clinical", "decision support", "deep learning", "prediction", "decision support", "deep learning", "clinical", "decision support", "interface", "medical"]}, {"paperID": "2597", "keywords": ["visual", "analytics", "clinician", "health", "health", "clinician", "clinician", "visual", "interface", "clinicians", "interactive", "graphical", "interface", "interface", "health", "health", "clinician", "health", "visual", "analytics", "visualization", "clinician", "medical", "health", "visual", "analytics", "health", "medical", "clinical", "clinical", "decision support", "visualization", "health", "machine learning", "health", "telemedicine", "health", "machine learning", "telemedicine"]}, {"paperID": "2598", "keywords": ["electronic health record", "visualization", "interactive", "algorithm", "visualization", "exploration", "visualization", "visualizations", "interactive", "medical", "visualization", "medical", "visualization", "visual", "analytics", "health", "medical", "visualization", "visual", "analytics", "visualization"]}, {"paperID": "2599", "keywords": ["interactive", "electronic health records", "data mining", "healthcare", "interactive", "visualizations", "explore", "clinical", "clinical", "interactive", "interface", "explored", "clinical", "medical", "data mining", "data mining"]}, {"paperID": "2601", "keywords": ["clinical", "big data", "interactive", "visualization", "visualization", "interactive", "data mining", "medical", "big data"]}, {"paperID": "2604", "keywords": ["prediction", "predictive", "electronic health record", "medicine", "clinical", "deep learning", "healthcare", "prediction", "algorithm", "predicting", "clinical", "predicting", "interactive", "visualization", "predicted", "prediction", "predicted", "prediction", "predictions", "deep learning", "electronic health record", "predictive", "medical", "algorithm", "clinical", "electronic health record", "predictive", "algorithms", "clinical", "deep learning", "electronic health records", "predictive"]}, {"paperID": "2605", "keywords": ["health", "analytics", "health", "exploratory", "health", "visual", "interface", "visualization", "health", "health", "visually", "exploratory", "health", "exploratory", "visualization", "medical", "visualization", "algorithm", "interface", "electronic health record", "health", "medical", "medical", "algorithms", "clinical", "electronic health records", "medical", "health", "health", "interface"]}, {"paperID": "2606", "keywords": ["biomedical", "visual", "analytics", "interactively", "visual", "machine learning", "visual", "visual"]}, {"paperID": "2607", "keywords": ["prediction", "visualization", "prediction", "prediction", "graphical", "interface", "predict", "visualize", "interactive", "visualization", "interface", "prediction", "graphical", "visualization", "interactive", "visualizations", "medical", "clinical", "visualization", "medicine", "prediction"]}, {"paperID": "2608", "keywords": ["visualization", "healthcare", "exploration", "health", "medical", "health", "medical", "interactive", "exploring", "medical", "visualization", "visual", "analytics", "big data", "health", "visualization", "healthcare", "interactive", "medical", "visual", "analytics", "visualization"]}, {"paperID": "2628", "keywords": ["visual", "machine learning", "visual", "analytics", "explore", "visual", "visual", "machine learning", "healthcare", "machine learning", "machine learning", "visual", "analytics", "graphical", "machine learning", "health", "machine learning", "visual", "analytics", "visual", "visual", "visualization"]}, {"paperID": "2630", "keywords": ["clinical", "decision support", "healthy", "clinical", "decision support", "prediction", "interactive", "dashboard", "visualization", "algorithm", "predictive", "prediction", "interactive", "visualization", "interface", "clinicians", "interface", "visualization", "medical", "clinical", "decision support", "interface", "medicine", "decision support", "clinical", "medicine", "interface"]}, {"paperID": "2631", "keywords": ["exploration", "interactions", "interactions", "health", "machine learning", "visual", "analytics", "interaction", "visualizations", "interaction", "machine learning", "interactively", "exploring", "interactions", "algorithms", "machine learning", "visualization", "interactions", "machine learning", "visual", "analytics", "interactions"]}, {"paperID": "2632", "keywords": ["algorithms", "prediction", "decision support", "interactive", "decision support", "decision support", "graphical", "interface", "explore", "prediction", "clinical", "medical", "algorithm", "decision support", "prediction", "interface", "interface"]}, {"paperID": "2633", "keywords": ["health", "visual", "analytics", "interactive", "visual", "machine learning", "prediction", "visualization", "visualization", "visualization", "interactive", "visual", "machine learning", "prediction"]}, {"paperID": "2640", "keywords": ["interactive", "clinical", "healthy", "visual", "analytics", "exploratory", "visualizations", "visually", "algorithms", "visualization", "healthy", "visual", "analytics"]}, {"paperID": "2647", "keywords": ["predict", "machine learning", "exploratory", "explore", "health", "algorithms", "predictive", "analytics", "predict", "interface", "medication", "healthcare", "analytics", "machine learning", "predictive", "analytics", "machine learning", "predictive", "analytics", "exploratory", "health"]}, {"paperID": "2648", "keywords": ["visual", "analytics", "interactive", "medical", "medical", "medications", "predict", "prediction", "clinical", "interactively", "visual", "analytics", "interactivity", "medical", "artificial intelligence", "visual", "analytics", "visual", "analytics", "interactive", "visualizations", "exploration", "prediction", "medical", "predictions", "interactivity", "interactive", "visual", "analytics", "healthcare", "interactive", "artificial intelligence", "deep learning", "artificial intelligence", "deep learning", "health", "medical", "medical", "predictive", "analytics", "visualization", "medical", "predictive", "visual", "analytics", "artificial intelligence"]}, {"paperID": "2657", "keywords": ["visualization", "healthcare", "healthcare", "health", "big data", "big data", "analytics", "interactive", "visualization", "visually", "machine learning", "algorithms", "visualization", "interactively", "algorithms", "prediction", "visualization", "interactive", "visualization"]}, {"paperID": "2659", "keywords": ["visual", "healthy", "medical", "big data", "interactive", "visual", "exploration", "explorative", "analytics", "visualization", "medicine", "medical", "medical", "biomedical", "visualization"]}, {"paperID": "2663", "keywords": ["visual", "analytics", "clinical", "health", "clinicians", "clinical", "visual", "analytics", "clinical", "clinician", "clinical", "interactive", "visual", "interface", "clinicians", "clinicians", "clinical", "clinician", "clinical", "visualizing", "clinicians", "interface", "visual", "analytics", "visualization", "visualization", "visualization", "visualization", "interface", "visual", "analytics", "medical", "algorithm", "machine learning", "algorithms", "machine learning"]}, {"paperID": "2664", "keywords": ["interactive", "automated", "graphical", "interface", "interactive", "interactive", "interactive", "bioinformatics", "graphical", "graphical", "interactive"]}, {"paperID": "2666", "keywords": ["interactive", "exploration", "visual", "analytics", "interactive", "exploration", "clinical", "clinically", "explored", "prediction", "prediction", "exploratory", "predictive", "visual", "analytics", "visual", "analytics", "predictive", "analytics", "visualization", "exploratory", "visual", "analytics"]}, {"paperID": "2667", "keywords": ["visualization", "algorithms", "interactive", "graphical", "interface", "exploring", "interactive", "visualisation", "predicted", "interactive", "interface", "visualisation", "explore", "interactive", "visualization", "medical", "bioinformatics", "prediction"]}, {"paperID": "2668", "keywords": ["interactive", "visual", "visualization", "visualization", "visualize", "interactive", "visual", "data mining", "visualization", "data mining", "interactive", "visualization", "algorithms", "interactive", "visual", "medical", "clinical", "data mining", "algorithm"]}, {"paperID": "2669", "keywords": ["interactive", "interactive", "graphical", "interactive", "interactivity", "interactive", "explored", "prediction", "interaction", "explore", "interactive", "graphical", "interface", "predictions", "graphical", "interface", "medical", "bioinformatics", "prediction", "interaction"]}, {"paperID": "2687", "keywords": ["automated", "analytics", "medical", "biomedical", "clinicians", "clinical", "decision support", "analytics", "clinical", "interface", "graphical", "graphical", "automated", "medical", "analytics", "biomedical", "decision support", "interactive", "medical", "biomedical", "clinical", "decision support", "medical", "medical", "clinical", "clinical", "decision support", "medical"]}, {"paperID": "2696", "keywords": ["visual", "decision support", "predictive", "interactive", "decision support", "visualization", "clinicians", "clinician", "predictions", "clinical", "decision support", "visualization", "medical", "clinical", "decision support", "clinical", "predictive", "visual", "decision support", "interface", "decision support", "interface"]}, {"paperID": "2703", "keywords": ["healthcare", "data mining", "health", "prediction", "clinical", "decision support", "data mining", "clinical", "prediction", "interactive", "dashboard", "data mining", "healthcare"]}, {"paperID": "2709", "keywords": ["visual", "exploration", "big data", "algorithms", "algorithmic", "visualization", "visual", "analytics", "exploration", "visualize", "interactively", "biomedical", "exploration", "visual", "analytics", "big data", "visualization", "visual", "analytics"]}, {"paperID": "2710", "keywords": ["exploring", "artificial intelligence", "clinical", "predict", "data mining", "visual", "analytics", "clinicians", "explore", "data mining", "visual", "analytics", "data mining", "visualization", "visual", "analytics", "medical"]}, {"paperID": "2713", "keywords": ["clinical", "clinicians", "clinicians", "predictive", "clinical", "decision support", "explore", "visualization", "decision support", "artificial intelligence", "medical", "clinical", "decision support", "decision support"]}, {"paperID": "2715", "keywords": ["interactive", "analytics", "interaction", "health", "interactive", "visual", "analytics", "algorithm", "interactions", "analytics", "interact", "visualizations", "visual", "analytics", "data mining", "visualization", "interactions", "health", "visual", "analytics", "visual", "analytics", "interactions"]}, {"paperID": "2718", "keywords": ["visual", "analytics", "visual", "analytics", "clinicians", "clinically", "interactive", "visualization", "clinically", "visual", "analytics", "clinicians", "medical", "visual", "analytics", "medical", "clinical", "clinical", "clinical", "medical", "automated", "graphics", "interface", "graphics", "visualization", "health", "automated", "interface"]}, {"paperID": "2719", "keywords": ["explore", "graphical", "exploratory", "algorithm", "clinical", "medical", "clinical"]}, {"paperID": "2720", "keywords": ["interactive", "visualization", "health", "interactive", "visualization", "decision support", "visualization", "healthcare", "clinical", "analytics", "visualization", "big data", "healthcare", "interactive", "visualization", "health", "visualize", "interactively", "healthcare", "interactive", "visualizing", "big data", "interactive", "visualization", "interactive", "visualizations", "healthcare", "interactive", "exploring", "big data", "interactive", "visualization", "healthcare", "data mining", "interactive", "visualization", "health", "big data", "data mining", "decision support", "health", "health", "visualization", "interactive", "visualizations", "visualization", "medical", "data mining", "health", "clinical", "medical", "health", "health", "big data", "visualization", "health"]}, {"paperID": "2721", "keywords": ["decision support", "clinical", "decision support", "interactive", "visualization", "interface", "decision support", "graphical", "interface", "visualization", "medical", "decision support", "medical", "algorithm", "clinical", "decision support"]}, {"paperID": "2722", "keywords": ["visualizing", "visual", "analytics", "healthcare", "health", "visual", "analytics", "medical", "clinical", "visual", "analytics", "visual", "analytics", "visualization", "interaction", "visualization", "health", "visualization", "visual", "analytics", "artificial intelligence", "visualization", "health", "visualization", "interaction", "visual", "analytics", "visualization"]}, {"paperID": "2733", "keywords": ["clinical", "big data", "algorithm", "health", "data mining", "visual", "analytics", "clinical", "clinical", "algorithm", "clinical", "electronic health records", "clinical", "interface", "interactive", "visualization", "algorithm", "interface", "algorithm", "interface", "medical", "algorithm", "data mining", "electronic health record", "algorithms", "big data", "data mining", "electronic health records"]}, {"paperID": "2738", "keywords": ["visual", "electronic health record", "visualization", "visualization", "visual", "visualization", "visual", "analytics", "interactive", "exploration", "visualization", "predictive", "visual", "analytics", "visual", "data mining", "graphical", "visualization", "algorithm", "visual", "analytics", "visual", "visualization"]}, {"paperID": "2742", "keywords": ["visual", "electronic health records", "visually", "explore", "visualization", "visualizes", "interactively", "visualization", "visual", "visual", "algorithms", "visualization", "visualization", "graphical", "visualization", "algorithm", "visualization", "visual", "visual"]}, {"paperID": "2745", "keywords": ["machine learning", "healthcare", "analytics", "clinical", "ai", "visualization", "visualization", "interaction"]}, {"paperID": "2752", "keywords": ["visual", "machine learning", "algorithms", "algorithms", "algorithms", "visual", "analytics", "visual", "interface", "explore", "visualization", "medical", "interactive", "visual", "visual", "analytics", "visualization", "visualization", "algorithms", "visual", "analytics", "visual", "algorithms"]}, {"paperID": "2758", "keywords": ["explorative", "visual", "analytics", "exploration", "visualization", "interactive", "analytics", "exploratory", "visualization", "explorer", "interactive", "analytics", "exploration", "visualization", "explorative", "interaction", "visualizations", "bioinformatics", "exploration", "interactive", "visual", "analytics", "visualization", "visualization", "exploration", "visualization", "visualization", "visual", "analytics", "visualization", "medical", "automated", "automated", "interaction"]}, {"paperID": "2761", "keywords": ["visual", "big data", "algorithms", "interactive", "visual", "analytics", "visualization", "visual", "analytics", "explore", "explore", "visual", "analytics", "algorithm", "data mining", "medical", "visualization", "visual", "analytics"]}, {"paperID": "2764", "keywords": ["clinical", "interactive", "visualization", "graphical", "interactive", "visualization", "visualization", "interface", "medical", "data mining", "data mining"]}, {"paperID": "2765", "keywords": ["visual", "interactively", "explored", "visual", "medical", "clinical", "clinical", "algorithm", "algorithms"]}, {"paperID": "2768", "keywords": ["visual", "dashboard", "dashboard", "visual", "analytics", "exploring", "medical", "dashboard", "interactive", "exploration", "data mining", "algorithm", "dashboard", "exploration", "visualizing", "health", "visual", "analytics", "data mining", "health", "visualization", "exploration", "health", "interactive", "exploration", "visual", "analytics", "visual", "analytics"]}, {"paperID": "2771", "keywords": ["interactive", "interactions", "interactions", "interactions", "interaction", "interactions", "interactions", "interface", "exploration", "algorithmic", "interactions", "bioinformatics", "interactions", "algorithmic", "interaction", "medical", "graphics", "interface", "graphics", "interface"]}, {"paperID": "2774", "keywords": ["interactive", "exploring", "machine learning", "predictive", "healthcare", "analytics", "predicting", "medicine", "machine learning", "predict", "interactive", "interface", "machine learning", "visualization", "exploring", "visual", "interface", "exploration", "predictions", "machine learning", "machine learning", "predictions", "visualization", "visual", "interface", "artificial intelligence", "predictive", "analytics", "visualization", "interactive", "machine learning", "predictive"]}, {"paperID": "2775", "keywords": ["interactive", "visual", "analytics", "predictions", "interactive", "visual", "analytics", "predictions", "prediction", "prediction", "algorithms", "prediction", "analytics", "predict", "prediction", "algorithms", "interactive", "visualization", "prediction", "interface", "predict", "visualize", "predict", "exploration", "prediction", "prediction", "interactive", "prediction", "visualization", "medical", "algorithm", "bioinformatics", "interface", "prediction", "exploration", "interface", "algorithms", "interface"]}, {"paperID": "2777", "keywords": ["interactive", "visual", "analytics", "medical", "medical", "visual", "analytics", "exploring", "visualization", "clinical", "interactivity", "medical", "visual", "analytics", "algorithms", "graphics", "visualization", "interactivity", "visual", "analytics", "visual", "analytics", "medical"]}, {"paperID": "2778", "keywords": ["interactive", "visualization", "interactive", "visualization", "interactive", "visualization", "interactive", "visualization", "visualization", "medical", "bioinformatics", "clinical", "algorithm", "graphics", "algorithms", "graphics"]}, {"paperID": "2779", "keywords": ["healthcare", "data mining", "health", "prediction", "clinical", "decision support", "data mining", "clinical", "prediction", "interactive", "dashboard", "data mining", "healthcare"]}, {"paperID": "2781", "keywords": ["interactive", "visualization", "interactive", "visualization", "interactive", "visualization", "interactive", "visualization", "visualization", "medical", "bioinformatics", "clinical", "algorithm", "graphics", "algorithms", "graphics"]}, {"paperID": "2782", "keywords": ["bioinformatics", "interface", "graphical", "healthy", "graphically", "visualized", "interactive", "medical", "data mining", "interface", "data mining", "interface"]}, {"paperID": "2798", "keywords": ["interactive", "visual", "analytics", "medical", "interactive", "visual", "analytics", "medical", "visualization", "visualizing", "interactive", "visualization", "interactive", "visualization", "interactive", "medical", "interactive", "visualization", "interactive", "medical", "visualization", "medical", "visualization", "interactive", "interactive", "visualization", "interactive", "visualizations", "visualization", "medical", "algorithm", "interface", "medical", "algorithms", "medical", "interface"]}, {"paperID": "2806", "keywords": ["visual", "predictor", "predict", "clinical", "clinicians", "medical", "algorithm", "visual", "analytics", "interactive", "visual", "visual", "analytics", "medical", "algorithm", "clinical", "algorithms", "clinical"]}, {"paperID": "2809", "keywords": ["interactive", "visualization", "exploration", "medical", "electronic health records", "clinical", "healthcare", "clinical", "visual", "analytics", "explore", "healthcare", "visualization", "visualization", "interactively", "explore", "medical", "interface", "data mining", "decision support", "electronic health record", "data mining", "electronic health records", "interface"]}, {"paperID": "2810", "keywords": ["visual", "analytics", "healthcare", "healthcare", "visual", "predict", "health", "algorithm", "explore", "visualization", "health", "healthcare", "visual", "analytics"]}, {"paperID": "2815", "keywords": ["interactive", "visual", "analytics", "healthcare", "clinical", "visual", "analytics", "interactively", "visualize", "explore", "visual", "analytics", "biomedical", "medical", "visualization", "clinical", "interactive", "visual", "analytics", "data mining"]}, {"paperID": "2821", "keywords": ["electronic health records", "graphical", "electronic health record", "health", "health", "algorithm", "health", "health", "health", "interface", "interaction", "big data", "health", "electronic health record", "graphical", "health", "health", "interaction", "graphical"]}, {"paperID": "2822", "keywords": ["healthcare", "interface", "interact", "interface", "analytics", "machine learning", "algorithms", "machine learning", "algorithms", "machine learning", "algorithms", "machine learning", "algorithms", "biomedical", "data mining", "machine learning", "artificial intelligence", "interface", "data mining", "medical", "biomedical", "interface", "algorithms"]}, {"paperID": "2823", "keywords": ["interface", "algorithm", "visualize", "interact", "interface", "medical", "bioinformatics", "interface", "algorithm", "algorithm", "algorithms"]}, {"paperID": "2824", "keywords": ["health", "health", "big data", "interactive", "visual", "health", "analytics", "interaction", "data mining", "health", "health", "interaction", "big data"]}, {"paperID": "2825", "keywords": ["visualization", "visualization", "visualization", "visualization", "interactively", "visualization", "graphics", "graphics", "interactive", "biomedical", "visualization", "graphics", "graphics", "visualization", "graphics", "medical", "graphics", "visualization", "visualization", "medical", "algorithm", "algorithms"]}, {"paperID": "2862", "keywords": ["visual", "analytics", "health", "automated", "visual", "analytics", "visual", "analytics", "decision support", "health", "visual", "analytics", "automated", "prediction", "visual", "analytics", "interactive", "visualization", "prediction", "interactive", "analytics", "health", "health", "health", "decision support", "health", "health", "health", "medical", "decision support", "health", "health", "health", "health", "prediction", "visual", "analytics", "health"]}, {"paperID": "2863", "keywords": ["predicting", "health", "decision support", "interactive", "visual", "analytics", "interactively", "predictive", "predicted", "decision support", "artificial intelligence", "decision support", "predictive"]}, {"paperID": "2868", "keywords": ["interacting", "predictions", "visual", "machine learning", "predictive", "interactive", "visual", "analytics", "interactive", "prediction", "predicted", "prediction", "predictive", "medical", "interactive", "machine learning", "visualization", "predictive", "visual", "analytics", "artificial intelligence", "interaction", "medical", "predictive", "analytics", "visualization", "interactive", "machine learning", "visualization", "predictive", "visual", "analytics"]}, {"paperID": "2869", "keywords": ["explora", "exploration", "explora", "algorithm", "explora", "explora", "interface", "graphically", "bioinformatics", "explora", "medical", "algorithm", "graphics", "algorithms", "graphics"]}, {"paperID": "2871", "keywords": ["explora", "exploration", "explora", "algorithm", "explora", "explora", "interface", "graphically", "bioinformatics", "explora", "medical", "algorithm", "graphics", "algorithms", "graphics"]}, {"paperID": "2874", "keywords": ["explorative", "exploring", "visual", "analytics", "visualization", "exploration", "medical", "explorative", "algorithms", "visual", "visualization", "visualization", "medical", "algorithm", "visual", "visual", "analytics", "algorithms"]}, {"paperID": "2879", "keywords": ["visual", "medical", "data mining", "automated", "algorithms", "explore", "algorithms", "visual", "exploring", "visualization", "algorithms", "visual", "data mining", "visual", "data mining", "data mining", "data mining", "visual", "algorithm", "data mining", "algorithms", "interactive", "interface", "visual", "data mining", "visual", "data mining", "clinical", "data mining", "medical", "visualization", "visualization", "visualization", "medical", "visualization", "automated", "algorithms", "data mining", "algorithm", "data mining", "algorithm", "interactive", "medical", "visualization", "data mining"]}, {"paperID": "2883", "keywords": ["visual", "analytics", "exploration", "medical", "medicine", "medical", "interactive", "visually", "explore", "medical", "visual", "exploration", "medical", "exploration", "exploration", "visual", "analytics", "algorithms", "visualization", "visualization", "exploration", "visual", "analytics", "visual", "exploration", "medical", "data mining"]}, {"paperID": "2888", "keywords": ["visual", "analytics", "big data", "visual", "analytics", "visual", "analytics", "interactive", "visualisations", "analytics", "medicines", "automated", "visualisation", "interaction", "exploration", "visualise", "interactive", "visual", "visualisation", "interactive", "visualisation", "medicines", "visual", "analytics"]}, {"paperID": "2889", "keywords": ["medical", "interactive", "machine learning", "interactive", "machine learning", "visualization", "interactions", "medical", "interface", "algorithm", "interactive", "machine learning", "visual", "analytics"]}, {"paperID": "2891", "keywords": ["analytics", "medical", "medical", "medical", "medical", "medical", "exploring", "medical", "automated", "medical", "medical", "dashboard", "data mining", "graphical", "interface", "medical", "interface", "data mining", "data mining", "interface"]}, {"paperID": "2910", "keywords": ["biomedical", "automated", "interactive", "visualizations", "medical"]}, {"paperID": "2912", "keywords": ["biomedical", "automated", "interactive", "visualizations", "medical"]}, {"paperID": "2915", "keywords": ["visual", "biomedical", "biomedical", "exploration", "visual", "analytics", "interactive", "interactive", "clinical", "interactive", "visualization", "biomedical", "interactive", "interactive", "visualizations", "visualization", "medical", "graphics", "data mining", "graphics", "data mining"]}, {"paperID": "2918", "keywords": ["interactive", "visual", "interact", "interactivity", "interactive", "visual", "interactive", "visual", "bioinformatics", "visual", "medical", "bioinformatics", "interface", "interactive", "visual", "interface", "data mining", "data mining", "interface"]}, {"paperID": "2923", "keywords": ["visual", "analytics", "health", "interactive", "visual", "exploration", "explore", "clinical", "visual", "analytics", "medical", "clinical", "automated", "interface", "health", "automated", "interface"]}, {"paperID": "2930", "keywords": ["visual", "predict", "visualization", "visual", "analytics", "interactively", "visualize", "explore", "medical", "visualization", "medical", "decision support", "visualization", "artificial intelligence", "visualization", "decision support", "visualization", "graphical", "visualization", "medical", "decision support"]}, {"paperID": "2934", "keywords": ["visualizing", "visualizing", "visualization", "interactive", "visualization", "visualizations", "visualization", "visualization", "medical", "bioinformatics", "algorithm", "interaction", "interaction"]}, {"paperID": "2937", "keywords": ["visual", "analytics", "interactively", "bioinformatics", "bioinformatics", "algorithms", "visual", "analytics", "interactively", "visual", "visualization", "interactive", "visualizations", "algorithms", "algorithms", "visualizations", "interactions", "exploration", "bioinformatics", "visualization", "bioinformatics", "visualization", "bioinformatics", "interactive", "visualizations", "visual", "visualization", "algorithms", "medical", "bioinformatics", "visual", "algorithm", "graphics", "algorithms", "graphics"]}, {"paperID": "2938", "keywords": ["electronic health records", "clinical", "visual", "clinicians", "predictive", "algorithm", "clinical", "explore", "interactive", "visualization", "healthcare", "health", "visualization", "clinical", "electronic health record", "visual", "interactive", "visualization", "predictive", "algorithms"]}, {"paperID": "2944", "keywords": ["prediction", "health", "electronic health record", "health", "predicting", "health", "health", "clinical", "medical", "predictive", "healthinfonet", "health", "health", "predictive", "exploration", "predicted", "clinical", "predictive", "algorithm", "clinicians", "health", "medical", "medical", "health", "medical", "electronic health record", "health", "health", "electronic health records", "health"]}, {"paperID": "2947", "keywords": ["visual", "analytics", "exploration", "medical", "visual", "medical", "clinical", "algorithms", "medical", "visual", "exploration", "visual", "analytics", "medical", "visual", "analytics", "interactive", "exploration", "medical", "visual", "analytics", "medical", "visualization", "medical", "interactive", "exploration", "visual", "analytics", "visual", "exploration", "medical", "automated", "interface", "automated", "interface"]}, {"paperID": "2950", "keywords": ["visual", "analytics", "automated", "automated", "interactively", "visual", "analytics", "automated", "interactive", "visual", "analytics", "medical", "visualization", "interactive", "visual", "analytics"]}, {"paperID": "2953", "keywords": ["decision support", "decision support", "interactive", "graphical", "interface", "decision support", "healthcare", "artificial intelligence", "graphical", "health", "decision support", "interactive", "graphical", "interface", "decision support"]}, {"paperID": "2954", "keywords": ["visualizations", "interact", "interacting", "interact", "visualization", "analytics", "explore", "interactions", "bioinformatics", "algorithm", "interacting", "interactions", "explored", "visually", "analytics", "interactive", "visualize", "interactions", "explore", "bioinformatics", "graphics", "visualization", "visualization", "interactive", "interactions"]}, {"paperID": "2955", "keywords": ["visual", "analytics", "interactive", "visual", "visualises", "visual", "analytics", "healthy", "visual", "analytics", "artificial intelligence", "visualization", "healthy", "visual", "analytics"]}, {"paperID": "2958", "keywords": ["visual", "analytics", "exploration", "medical", "predict", "algorithms", "visual", "algorithms", "explore", "exploration", "algorithm", "exploration", "explore", "visual", "algorithms", "medical", "algorithms", "visual", "analytics"]}, {"paperID": "2964", "keywords": ["visual", "analytics", "clinical", "decision support", "visual", "analytics", "clinical", "decision support", "medical", "explore", "clinical", "decision support", "data mining", "medical", "analytics", "visual", "analytics", "data mining", "decision support", "medical", "visualization", "clinical", "decision support", "medical", "analytics", "visual", "analytics", "big data"]}, {"paperID": "2969", "keywords": ["data mining", "clinical", "analytics", "data mining", "clinical", "clinical", "clinical", "clinical", "analytics", "clinical", "data mining", "data mining", "interactive", "visualizations", "clinical", "clinical", "clinical", "clinical", "clinical", "data mining", "interactive", "visualization", "bioinformatics", "visualization", "medical", "visualization", "clinical", "clinical", "interactive", "visualizations", "data mining"]}, {"paperID": "2970", "keywords": ["interactive", "exploratory", "visualization", "medical", "clinical", "medical", "clinical", "interactive", "visually", "visualization", "visually", "interactive", "visualizations", "visual", "exploratory", "automated", "visual", "visualization", "medical", "clinical", "electronic health record", "health", "clinical", "electronic health records", "health"]}, {"paperID": "2975", "keywords": ["visualization", "predictive", "predictive", "prediction", "medical", "electronic health records", "visualization", "medical", "exploration", "predictive", "exploration", "predictive", "predictive", "interactive", "visualizations", "medical", "electronic health record", "machine learning", "electronic health records", "machine learning"]}, {"paperID": "2978", "keywords": ["visual", "analytics", "interactive", "visualization", "exploring", "clinical", "decision support", "visualization", "artificial intelligence", "decision support", "health", "visualization", "clinical", "decision support", "visualization", "visualization"]}, {"paperID": "2980", "keywords": ["interactive", "visual", "decision support", "interactive", "visual", "analytics", "decision support", "interactive", "visual", "visual", "medical", "decision support", "decision support", "visualization", "artificial intelligence", "visualization", "visualization", "medical", "visualization", "medical", "visual", "analytics", "visual", "visual", "decision support"]}, {"paperID": "2981", "keywords": ["medical", "machine learning", "interactive", "machine learning", "visualization", "interactions", "medical", "interface", "algorithm", "interactive", "machine learning", "visual", "analytics", "artificial intelligence", "data mining", "algorithms", "visualization", "interactive", "machine learning", "visual", "analytics", "medical"]}, {"paperID": "2982", "keywords": ["clinical", "dashboard", "clinical", "health", "interactive", "visualisation", "analytics", "clinical", "dashboard", "healthcare", "visualization", "clinical", "visualising", "biomedical", "healthcare", "visualisations", "clinical", "visualisation", "healthcare", "clinical", "visualise", "health", "visualise", "clinical", "visualisation", "health", "medical", "visualisations", "visualisations", "predictions", "medicine", "visualisation", "health", "clinical", "visualisation", "medical", "clinical", "medical", "health", "health", "health", "medical", "medical", "medicine", "medical", "health", "medical"]}, {"paperID": "2983", "keywords": ["visual", "decision support", "medical", "visual", "data mining", "medical", "visual", "data mining", "graphical", "interactive", "machine learning", "medical", "visualizing", "visual", "decision support", "medical", "data mining", "visualization", "medical", "medical", "data mining", "decision support", "medical", "visualization", "artificial intelligence", "visualization", "decision support", "visualization", "medical", "visualization", "graphical", "decision support", "interactive", "machine learning", "medical", "medical", "visualization", "data mining"]}, {"paperID": "3012", "keywords": ["visual", "analytics", "clinical", "algorithms", "interactive", "analytics", "machine learning", "clinical", "visualization", "exploration", "algorithmically", "medical", "machine learning"]}, {"paperID": "3018", "keywords": ["visual", "analytics", "interactive", "visual", "biomedicine", "medicine", "graphical", "interactive", "visualizing", "visualization", "exploration", "visual", "interface", "algorithms", "visual", "medical", "algorithm", "interface", "interaction", "algorithms", "graphics", "data mining", "interaction"]}, {"paperID": "3020", "keywords": ["automated", "clinical", "clinical", "clinical", "clinical", "automated", "algorithm", "interactive", "interface", "clinical", "clinical", "decision support", "clinical", "clinical", "medical", "algorithm", "interface", "decision support", "medical", "health", "health"]}, {"paperID": "3026", "keywords": ["visual", "analytics", "visual", "exploration", "analytics", "algorithms", "visual", "analytics", "algorithm", "interact", "algorithm", "visual", "analytics", "algorithms", "visualization", "interactions", "visual", "analytics", "algorithms", "visualizations", "visual", "analytics", "visual", "analytics", "visual", "analytics", "clinical", "medical", "medical", "visualization", "interactive", "machine learning", "visual", "analytics", "medical", "visualization", "interactive", "machine learning", "visual", "analytics", "visual", "exploration", "medical", "algorithm", "graphics", "interface", "electronic health record", "machine learning", "algorithms", "graphics", "electronic health records", "machine learning", "interface"]}, {"paperID": "3029", "keywords": ["interactive", "predictive", "predictive", "predicted", "predictive", "algorithms", "algorithms", "algorithmic", "visual", "analytics", "predictive", "algorithms", "clinical", "predicting", "medical", "predictive", "visual", "analytics", "interactive", "predictive", "visual", "analytics", "medical", "algorithm", "graphics", "interface", "algorithms", "graphics", "interface"]}, {"paperID": "3032", "keywords": ["interactive", "visual", "exploration", "clinical", "clinical", "medicine", "health", "explorer", "visual", "clinical", "exploration", "visualization", "visual", "exploration", "exploration", "medicine", "visual", "analytics", "visualization", "interactive", "visual", "medicines", "visual", "analytics", "medical", "algorithm", "clinical", "graphics", "medicine", "algorithms", "clinical", "graphics", "medicine"]}, {"paperID": "3036", "keywords": ["interactive", "visual", "visually", "medical", "visual", "analytics", "algorithms", "visualization", "interactive", "visual", "visual", "analytics"]}, {"paperID": "3041", "keywords": ["medical", "decision support", "predict", "interactive", "decision support", "medical", "visualizing", "medical", "decision support", "visualization", "interactive", "visualization", "data mining", "decision support", "artificial intelligence", "visualization", "decision support", "interaction", "medical", "visualization", "interactive", "decision support", "medical", "visualization", "data mining"]}, {"paperID": "3046", "keywords": ["visual", "analytics", "analytics", "exploratory", "analytics", "visual", "visual", "analytics", "automated", "interface", "medical", "visual", "analytics", "graphical", "visualization", "analytics", "exploratory", "visual", "analytics"]}, {"paperID": "3047", "keywords": ["medical", "visual", "analytics", "biomedical", "medical", "explore", "predict", "visualization", "visual", "analytics", "visual", "analytics", "biomedical", "medicine", "visualization", "biomedical", "visualization", "medical", "medical", "medical"]}, {"paperID": "3048", "keywords": ["interface", "clinical", "health", "automated", "health", "clinical", "clinical", "decision support", "health", "interface", "interactively", "health", "interface", "clinical", "decision support", "interactive", "interface", "interface", "interface", "artificial intelligence", "decision support", "health", "clinical", "decision support", "interface", "interface"]}, {"paperID": "3049", "keywords": ["exploring", "medical", "visual", "analytics", "explorer", "visualizes", "medical", "explorer", "algorithm", "visualized", "interactive", "interface", "visualizations", "clinical", "clinical", "explorer", "visualizations", "visualization", "visual", "analytics", "algorithms", "visualization", "medical", "visualization", "visualizations", "medical", "interactive", "visual", "analytics", "data mining", "medical", "explorer", "interface", "data mining", "medical", "medical", "algorithm", "graphics", "data mining", "electronic health record", "algorithms", "graphics", "data mining", "electronic health records"]}, {"paperID": "3050", "keywords": ["machine learning", "biomedical", "machine learning", "machine learning", "biomedical", "clinical", "interactive", "interface", "visualization", "machine learning", "artificial intelligence", "visualization", "interactive", "visualization"]}, {"paperID": "3051", "keywords": ["exploration", "predicting", "visual", "visual", "exploration", "data mining", "interactive", "visual", "clinical", "data mining", "explored", "visually", "clinical", "clinically", "exploration", "clinical", "interactive", "exploration", "prediction", "medical", "data mining", "visual", "analytics", "medical", "data mining", "exploratory", "clinical", "medical", "medical", "automated", "interface", "data mining", "data mining", "automated", "interface"]}, {"paperID": "3053", "keywords": ["exploration", "predicting", "visual", "visual", "exploration", "data mining", "interactive", "visual", "clinical", "data mining", "explored", "visually", "clinical", "clinically", "exploration", "clinical", "interactive", "exploration", "prediction", "medical", "data mining", "visual", "analytics", "medical", "data mining", "exploratory", "clinical", "medical", "medical", "automated", "interface", "data mining", "data mining", "automated", "interface"]}, {"paperID": "3054", "keywords": ["visual", "medical", "algorithms", "medical", "algorithms", "algorithms", "algorithms", "algorithms", "medical", "algorithmic", "interactive", "visualization", "algorithm", "algorithm", "algorithms", "interactive", "algorithm", "algorithms", "algorithms", "algorithms", "medical", "visual", "analytics", "visual", "algorithms", "visualization", "health", "interaction", "medical", "medical", "graphics", "visualization", "medical", "visual", "analytics", "visual", "algorithms"]}, {"paperID": "3055", "keywords": ["visual", "analytics", "healthcare", "health", "analytics", "visualization", "exploration", "dashboard", "dashboard", "medical", "medical", "visualization", "medical", "medical", "automated", "interface", "medical", "automated", "interface"]}, {"paperID": "3057", "keywords": ["visual", "analytics", "healthcare", "health", "analytics", "visualization", "exploration", "dashboard", "dashboard", "medical", "medical", "visualization", "medical", "medical", "automated", "interface", "medical", "automated", "interface"]}, {"paperID": "3074", "keywords": ["health", "algorithms", "visualisation", "graphically", "health", "exploration", "medical", "interactive", "visualising", "electronic health records", "electronic health record", "interactive", "medical", "health", "algorithms"]}, {"paperID": "3084", "keywords": ["visual", "analytics", "exploring", "predict", "visual", "analytics", "graphics", "interaction", "medical", "graphics", "interaction", "medical", "visual", "analytics", "graphics", "visualization"]}, {"paperID": "3086", "keywords": ["visual", "clinical", "clinical", "clinical", "clinical", "health", "medical", "visual", "analytics", "interactive", "visualization", "automated", "visually", "visualization", "medical", "visual", "analytics", "automated", "clinical", "clinical", "visualization", "interactive", "visualizations", "visual", "analytics", "visualization", "medical", "visualization", "medical"]}, {"paperID": "3089", "keywords": ["medical", "medical", "algorithms", "visual", "analytics", "interactive", "visualization", "algorithms", "algorithm", "algorithms", "medical", "medical", "visual", "analytics", "interactive", "visualizations", "medical", "algorithms", "visual", "analytics", "algorithms", "visualization", "medical", "medical", "visualization"]}, {"paperID": "3094", "keywords": ["visual", "electronic health records", "clinical", "dashboard", "explore", "visual", "interactive", "predictive", "clinical", "clinical", "dashboard", "interactive", "visualization", "visual", "clinical", "dashboard", "electronic health record", "interactive", "visualizations", "predictive", "visual", "visualization", "interaction"]}, {"paperID": "3095", "keywords": ["visualization", "biomedical", "visualization", "visualization", "algorithms", "interactive", "graphical", "interface", "visualization", "visualization", "interaction", "biomedical", "medical", "algorithms", "bioinformatics", "visualization", "medical", "algorithm", "graphics", "interface"]}, {"paperID": "3098", "keywords": ["medical", "health", "interactions", "algorithms", "visual", "analytics", "exploratory", "interactions", "algorithms", "exploratory", "interactions", "visual", "analytics", "algorithms"]}, {"paperID": "3111", "keywords": ["clinical", "decision support", "healthcare", "clinical", "decision support", "clinicians", "clinicians", "predicting", "clinically", "interactive", "dashboard", "predictive", "dashboard", "healthcare", "clinic", "decision support", "clinical", "electronic health records", "medical", "medication", "medical", "bioinformatics", "clinical", "clinical", "decision support", "clinical", "decision support", "medical"]}, {"paperID": "3112", "keywords": ["interactive", "visual", "clinical", "electronic health record", "medical", "health", "interactive", "visual", "exploration", "clinical", "visual", "interactively", "interactive", "visualization", "interactive", "visualization", "visual", "analytics", "data mining", "electronic health record", "interactive", "visualizations", "medical", "visual", "analytics", "visual", "exploration", "visualization", "medical", "algorithm", "clinical", "medical", "health", "medical", "data mining", "interactive", "visualization", "medical", "data mining", "medical", "algorithms", "data mining", "electronic health records", "medical"]}, {"paperID": "3113", "keywords": ["interactive", "biomedical", "bioinformatics", "biomedical", "biomedical", "bioinformatics", "interactive", "biomedical", "visual", "explorer", "visual", "analytics", "interaction", "biomedical", "graphics", "explorer", "graphic", "biomedical", "interactions", "visualization", "interaction", "visual", "bioinformatics", "data mining", "visualization", "graphical", "interaction", "interaction", "graphics", "visual", "medical", "algorithm", "bioinformatics", "interaction", "medical", "visualization", "interaction", "visual", "algorithms", "biomedical", "medical", "interface"]}, {"paperID": "3114", "keywords": ["visual", "biomedical", "biomedical", "data mining", "machine learning", "visualization", "visualization", "visualization", "interaction", "interaction", "interactively", "visualization", "interactive", "biomedical", "visual", "analytics", "visualization", "data mining", "visualization", "interaction", "visualization", "visual", "analytics", "visualization"]}, {"paperID": "3115", "keywords": ["exploration", "visual", "exploration", "biomedical", "interactions", "interactive", "visualization", "interface", "exploring", "predicting", "visualize", "interface", "visualizing", "visualizing", "interactive", "visualization", "medical", "interface", "interaction", "interface"]}, {"paperID": "3116", "keywords": ["clinical", "decision support", "algorithm", "clinical", "decision support", "interaction", "electronic health record", "analytics", "medical", "interface", "medical", "electronic health records", "medical", "medical", "medical", "algorithm", "decision support", "medical", "algorithms", "decision support", "clinical", "electronic health records"]}, {"paperID": "3117", "keywords": ["healthcare", "electronic health records", "data mining", "exploring", "algorithm", "healthcare", "healthcare", "visual", "analytics", "big data", "decision support", "data mining", "decision support", "algorithms", "decision support", "electronic health record", "health", "data mining", "decision support", "health", "data mining", "medical", "algorithm", "data mining", "health", "health", "health", "health", "health", "clinical", "decision support", "health", "data mining", "decision support"]}, {"paperID": "3118", "keywords": ["visual", "visualization", "exploration", "biomedical", "visualization", "algorithms", "visual", "exploration", "algorithm", "visualization", "interactive", "visual", "exploration", "bioinformatics", "medical", "graphics", "visualization", "biomedical", "interactive", "visual", "visual", "exploration", "visualization", "algorithms", "visualization"]}, {"paperID": "3128", "keywords": ["clinical", "bioinformatics", "clinical", "medicine", "clinical", "clinical", "algorithms", "clinical", "graphical", "interface", "interactive", "clinical", "clinical", "clinical", "clinical", "interactive", "medicines", "bioinformatics", "graphical", "medical", "algorithm", "algorithms"]}, {"paperID": "3129", "keywords": ["visual", "data mining", "visual", "analytics", "data mining", "visualization", "visual", "analytics", "visual", "visualize", "data mining", "data mining", "visual", "analytics", "data mining", "medical", "medical", "interactively", "data mining", "algorithms", "visually", "visualization", "data mining", "algorithms", "visualize", "visual", "visual", "visualization", "algorithm", "data mining", "data mining", "visual", "analytics", "visual"]}, {"paperID": "3130", "keywords": ["visual", "analytics", "medical", "medical", "clinical", "algorithms", "visual", "analytics", "medical", "visual", "interactive", "visual", "analytics", "medical", "medical", "visual", "analytics", "medical", "visualization", "clinical", "medical", "algorithms", "medical", "visual", "analytics", "medical"]}, {"paperID": "3132", "keywords": ["interactive", "visualization", "visual", "graphical", "predicted", "interactive", "graphical", "interface", "decision support", "health", "visualize", "medical", "graphics", "interface", "graphics", "interface"]}, {"paperID": "3141", "keywords": ["visualization", "health", "health", "health", "health", "health", "visualization", "visualization", "health", "visualize", "medical", "health", "interactive", "medical", "medical", "visualize", "decision support", "health", "visualization", "health", "visualization", "interactive", "medical", "visualization", "artificial intelligence", "decision support", "health", "visualization", "visualization"]}, {"paperID": "3149", "keywords": ["bioinformatics", "prediction", "bioinformatics", "prediction", "predictions", "prediction", "explored", "interface", "interface", "bioinformatics", "medical", "bioinformatics", "interface"]}, {"paperID": "3150", "keywords": ["visual", "analytics", "decision support", "predicting", "interactive", "decision support", "health", "interactive", "decision support", "explore", "interactively", "visualization", "decision support", "health", "visual", "analytics", "decision support", "graphical", "visualization"]}, {"paperID": "3156", "keywords": ["visual", "analytics", "clinical", "visual", "analytics", "clinical", "visualizing", "clinicians", "visual", "analytics", "data mining", "interactive", "visualization", "visual", "visual", "analytics", "visualization", "clinical", "interactive", "visualizations", "visual", "analytics", "data mining", "visualization", "visualization", "visualization"]}, {"paperID": "3162", "keywords": ["interactive", "visual", "visualization", "algorithm", "interaction", "healthcare", "visualization", "visual", "visualization", "healthcare", "visualization", "interactive", "visual", "algorithms", "interaction", "visual", "algorithms", "health", "visualization", "medical", "algorithm", "graphics", "interface", "algorithms", "graphics", "interface"]}, {"paperID": "3163", "keywords": ["bioinformatics", "interactive", "visual", "data mining", "interact", "bioinformatics", "interactive", "visual", "data mining", "bioinformatics", "data mining", "medical"]}, {"paperID": "3164", "keywords": ["interactive", "visually", "healthy", "automated", "analytics", "interactive", "visualization", "analytics", "visualizations", "explore", "interactively", "visualizations", "exploration", "medical"]}, {"paperID": "3165", "keywords": ["visual", "analytics", "visual", "analytics", "biomedical", "automated", "visualization", "interactive", "visualization", "visualizations", "medical", "visual", "interaction", "medical", "visualization", "visual", "analytics", "visualization", "health", "graphics", "medical", "visualization", "visual", "analytics", "visualization"]}, {"paperID": "3166", "keywords": ["visual", "analytics", "visual", "analytics", "visual", "analytics", "visual", "analytics", "interface", "prediction", "visual", "analytics", "visual", "analytics", "visualization", "interaction", "medical", "clinical", "prediction", "visual", "analytics", "interface"]}, {"paperID": "3167", "keywords": ["visual", "visual", "exploration", "interactive", "visual", "visualized", "visualizations", "interaction", "explored", "interactive", "visual", "analytics", "visual", "interaction", "bioinformatics", "visualization", "medical", "bioinformatics", "graphics", "data mining", "graphics", "data mining", "visual", "exploration"]}, {"paperID": "3187", "keywords": ["visual", "visual", "analytics", "medical", "medical", "interactively", "data mining", "algorithms", "visually", "visualization", "visualize", "visual", "visual", "visualization", "algorithm", "data mining", "visual", "visualization", "data mining", "algorithm", "medical", "visual", "analytics", "visual", "data mining", "medical", "medical", "visualization", "visualization"]}, {"paperID": "3188", "keywords": ["medicines", "clinical", "exploratory", "graphical", "visualising", "medical", "graphical", "medical", "medical", "medication", "electronic health records", "data mining", "electronic health record", "exploratory", "medical"]}, {"paperID": "3191", "keywords": ["interface", "medical", "interactive", "interface", "medical", "medical", "health", "medical", "health", "medical", "medical", "health", "machine learning", "data mining", "interactive", "interface", "medical"]}, {"paperID": "3192", "keywords": ["predictive", "healthcare", "decision support", "healthcare", "decision support", "dashboard", "dashboard", "predictive", "predicts", "predictive", "dashboard", "predictive", "explore", "dashboard", "interface", "decision support", "health", "decision support", "health", "predictive", "decision support", "health"]}, {"paperID": "3194", "keywords": ["visual", "analytics", "predicting", "predict", "visualize", "visualized", "visual", "visualization", "visualization", "visual", "analytics", "bioinformatics", "graphics", "graphics", "interactive", "exploration", "medical", "graphics", "graphics", "interactive", "exploration", "medical", "visual", "visual", "analytics", "bioinformatics", "graphical", "interactive", "graphics", "visualization"]}, {"paperID": "3195", "keywords": ["visualization", "visualizing", "visualization", "machine learning", "visualization", "interactive", "visualization", "exploratory", "visualization", "exploratory", "visualization", "visualization", "visualization", "bioinformatics", "medical", "automated"]}, {"paperID": "3196", "keywords": ["visual", "clinical", "electronic health records", "visualized", "interactive", "visual", "interactively", "visualization", "interactively", "medical", "medical", "algorithm", "graphics", "interface", "decision support", "medical", "algorithms", "graphics", "decision support", "clinical", "electronic health records", "interface"]}, {"paperID": "3197", "keywords": ["analytics", "visual", "exploration", "visual", "exploration", "machine learning", "interactive", "visualization", "automated", "machine learning", "interface", "visualization", "exploration", "interactive", "visualization", "machine learning", "visual", "exploration", "visual", "exploration", "visualization", "bioinformatics", "visualization", "visualization", "medical", "algorithm", "algorithms"]}, {"paperID": "3198", "keywords": ["visualisation", "interactive", "visualization", "visualize", "interactive", "medical", "bioinformatics", "graphics", "algorithm", "algorithms"]}, {"paperID": "3207", "keywords": ["visualization", "visualization", "visualization", "interactive", "graphic", "interactions", "algorithmic", "interface", "algorithmic", "interactive", "graphics", "interactions", "interface", "visualization", "visualization", "visualization", "visualization", "medical", "bioinformatics", "clinical", "interface", "interaction"]}, {"paperID": "3208", "keywords": ["visual", "analytics", "bioinformatics", "algorithms", "interactive", "visualization", "visualization", "visual", "analytics", "algorithm", "visual", "analytics", "visualization", "bioinformatics", "visualization", "medical", "bioinformatics", "graphics", "algorithm", "algorithm", "graphics", "interface", "algorithms", "graphics", "interaction", "interface"]}, {"paperID": "3209", "keywords": ["visualization", "clinical", "visualization", "exploration", "clinical", "decision support", "clinical", "medical", "visualize", "visualization", "visualization", "health", "clinical", "artificial intelligence", "decision support", "medical", "visualization", "clinical", "clinical", "decision support", "clinical", "clinical", "medical", "visualization"]}, {"paperID": "3233", "keywords": ["predictive", "visualization", "visualization", "visualization", "interactive", "visualization", "predictive", "medical", "bioinformatics", "graphics", "graphics"]}, {"paperID": "3239", "keywords": ["visualization", "graphical", "interface", "interactive", "data mining", "visualization", "medical", "bioinformatics", "graphics", "interface", "graphics", "interface"]}, {"paperID": "3240", "keywords": ["visualization", "visualization", "visualization", "visualization", "interactive", "visualization", "visualization", "clinical", "algorithm", "interactive", "visualization", "medical", "clinical", "visualization", "clinical", "medical", "algorithms", "clinical"]}, {"paperID": "3241", "keywords": ["visual", "visualization", "visually", "interactive", "biomedical", "medical", "bioinformatics", "interface", "algorithm", "algorithms", "artificial intelligence", "automated", "visual"]}, {"paperID": "3242", "keywords": ["algorithm", "automated", "medical", "interactive", "visualization", "algorithms"]}, {"paperID": "3243", "keywords": ["interactive", "visualization", "biomedical", "biomedical", "explore", "interactive", "visualization", "visualization", "biomedical", "biomedical", "algorithms", "visualization", "visualization", "interactive", "visualization", "biomedical", "medical", "algorithm", "bioinformatics", "biomedicine", "interface", "algorithms", "interface"]}, {"paperID": "3244", "keywords": ["clinicians", "interact", "visualize", "algorithm", "visualization", "algorithm", "algorithms", "medical", "algorithm", "algorithms"]}, {"paperID": "3245", "keywords": ["visualization", "explored", "visualized", "graphically", "medical", "bioinformatics", "algorithms", "graphics", "interface"]}, {"paperID": "3246", "keywords": ["interactive", "graphically", "clinical", "predicting", "medical", "clinical", "medical", "clinical", "predicting", "predicting", "prediction", "health", "medical"]}, {"paperID": "3247", "keywords": ["visualization", "explorative", "biomedical", "visualization", "biomedical", "explorative", "data mining", "visualization", "interactions", "biomedical", "explorative", "visualisation", "visualization", "data mining", "visualization", "explorative", "visualisation", "visualization", "biomedical", "medical", "machine learning", "medical", "algorithms", "artificial intelligence", "biomedical", "biomedical", "graphics", "interface"]}, {"paperID": "3255", "keywords": ["visualization", "biomedical", "biomedical", "exploratory", "visualization", "visualizing", "algorithm", "interface", "biomedical", "biomedical", "visualization", "biomedical", "medical"]}, {"paperID": "3256", "keywords": ["machine learning", "visualization", "clinical", "clinical", "clinically", "exploratory", "machine learning", "visualization", "clinically", "machine learning", "visualization", "algorithms", "exploratory", "exploratory", "bioinformatics", "biomedical", "data mining", "exploratory", "machine learning", "medicine", "visualization", "medical", "algorithm", "bioinformatics"]}, {"paperID": "3264", "keywords": ["health", "clinical", "decision support", "health", "clinical", "decision support", "interface", "clinical", "interactive", "visualization", "algorithms", "clinical", "decision support", "interface", "interface", "algorithms", "decision support", "data mining", "algorithms", "decision support", "biomedical", "data mining", "visualization", "decision support", "clinical", "decision support", "data mining", "algorithm", "algorithms", "interactive", "medical", "decision support", "telemedicine", "decision support", "clinical", "clinical", "telemedicine"]}, {"paperID": "3272", "keywords": ["machine learning", "explore", "data mining", "visual", "exploration", "visualization", "visualized", "algorithms", "visualize", "algorithm", "visualizations", "algorithms", "explore", "visualization", "bioinformatics", "machine learning", "algorithms", "visualization"]}, {"paperID": "3274", "keywords": ["visualizing", "automated", "visualization", "bioinformatics", "interactive", "exploration", "visual", "algorithms", "visual", "interaction", "prediction", "algorithms", "interaction", "graphical", "interface", "prediction", "predictions", "medical", "graphics", "interface", "algorithm", "prediction", "graphics", "interface", "graphical", "interface"]}, {"paperID": "3277", "keywords": ["visualization", "medical", "clinical", "visual", "decision support", "medical", "automated", "clinical", "visualized", "explored", "visualization", "visualization", "exploration", "medical", "artificial intelligence", "interface", "medical", "artificial intelligence", "medical", "interface"]}, {"paperID": "3283", "keywords": ["visualization", "interaction", "interaction", "graphical", "interface", "visualization", "interface", "interactions", "interactive", "visual", "interaction", "visualizing", "interaction", "predicted", "interactions", "interactions", "visualizations", "visualization", "visualization", "visualization", "medical", "graphics", "interface", "interaction", "medical", "medical", "interaction", "prediction", "graphics", "interaction", "explorer"]}, {"paperID": "3286", "keywords": ["interactive", "graphic", "interactive", "graphic", "interaction", "interface", "automated", "interface", "graphic", "interface", "interactive", "graphic", "medical", "medical", "graphics", "medical", "interface"]}, {"paperID": "3287", "keywords": ["biomedical", "interactively", "visualization", "data mining", "algorithm", "biomedical", "visually", "algorithms", "biomedical", "medicine"]}, {"paperID": "3288", "keywords": ["algorithms", "interface", "explore", "interface", "graphical", "bioinformatics", "interface", "medical", "interface", "algorithm", "graphics", "algorithms", "graphics", "interface"]}, {"paperID": "3289", "keywords": ["visual", "exploratory", "medical", "algorithms", "visual", "exploration", "biomedical", "algorithms", "visually", "explore", "visualization", "algorithms", "visual", "exploration", "medical", "algorithm", "biomedicine", "clinical"]}, {"paperID": "3290", "keywords": ["biomedical", "machine learning", "biomedical", "medical", "algorithm", "interactive", "algorithms", "visualization", "biomedical", "algorithm", "biomedical", "algorithms", "interactive"]}, {"paperID": "3291", "keywords": ["visual", "visual", "data mining", "explorative", "data mining", "visualization", "medical", "data mining", "visualization"]}, {"paperID": "3298", "keywords": ["interactive", "interactive", "visually", "visually", "algorithm", "interactive", "interaction", "graphics", "medical", "clinical"]}, {"paperID": "3303", "keywords": ["interaction", "medical", "decision support", "medical", "interface", "artificial intelligence", "medical", "decision support", "biomedical"]}, {"paperID": "3306", "keywords": ["clinical", "medical", "graphical", "interface", "interactively", "clinician", "artificial intelligence", "medical", "clinical", "medical", "decision support", "biomedical"]}, {"paperID": "3311", "keywords": ["health", "health", "decision support", "interactive", "interface", "health", "interactive", "medical", "artificial intelligence", "health", "interface"]}, {"paperID": "3312", "keywords": ["aeromedical", "visualization", "decision support", "automated", "visualization", "automated", "visualization", "interaction", "automated", "medical", "automated", "visualization", "automated", "medicine", "interaction", "interactive", "graphics", "medical", "visualization", "aeromedical", "decision support", "visualization", "medical", "medical", "decision support"]}, {"paperID": "3315", "keywords": ["decision support", "clinicians", "interface", "interactive", "algorithms", "decision support", "health", "medical", "algorithm", "algorithms", "healthcare"]}, {"paperID": "3318", "keywords": ["clinical", "interactive", "interface", "clinical", "algorithmic", "graphical", "interactive", "algorithmic", "graphical", "algorithm", "visualize", "algorithm", "clinical", "medical", "algorithm", "interface", "decision support", "algorithms", "decision support", "interface"]}, {"paperID": "3321", "keywords": ["clinical", "clinicians", "algorithms", "clinician", "interactive", "decision support", "medical", "algorithm", "clinical", "interface", "medical", "algorithms", "decision support"]}, {"paperID": "3322", "keywords": ["decision support", "decision support", "decision support", "interactive", "interface", "medical", "artificial intelligence", "decision support", "medical", "artificial intelligence"]}, {"paperID": "3327", "keywords": ["decision support", "visual", "decision support", "visual", "interaction", "clinical", "visual", "data mining", "visualization", "visual", "data mining", "decision support"]}, {"paperID": "3331", "keywords": ["decision support", "clinicians", "interface", "interactive", "algorithms", "clinicians", "health", "artificial intelligence", "interactive", "algorithms", "decision support", "interface", "decision support", "medical", "interface", "decision support", "health", "interface"]}, {"paperID": "3332", "keywords": ["health", "interactive", "interface", "medical", "algorithm", "interface", "decision support", "health", "algorithms", "decision support", "health", "interface"]}, {"paperID": "3335", "keywords": ["interactive", "automated", "decision support", "health", "interactive", "interface", "interactions", "health", "predictions", "predictions"]}, {"paperID": "3336", "keywords": ["interactively", "exploring", "bioinformatics", "algorithmic", "algorithms", "visualization", "explorer", "interactive", "visualization", "interact", "algorithms", "interactive", "visualization", "algorithms", "bioinformatics"]}, {"paperID": "3339", "keywords": ["visualisation", "clinical", "interactive", "exploration", "clinical", "medicine", "clinicians", "visualisation", "visualising", "clinical", "clinical", "clinician", "interaction", "exploring", "clinicians", "clinical", "interaction", "visualisation", "clinics", "clinical", "clinicians", "visualisation", "interactive", "exploration", "artificial intelligence", "visualization", "visualization", "medical", "medical"]}, {"paperID": "3340", "keywords": ["visualization", "interactive", "automated", "algorithms", "clinician", "algorithms", "visualization", "medical", "medical", "algorithm"]}, {"paperID": "3341", "keywords": ["interactive", "visualization", "exploration", "clinical", "visualization", "exploration", "clinical", "clinically", "interacting", "interacting", "clinical", "medical", "artificial intelligence", "interface", "decision support", "medical", "artificial intelligence", "medical", "interface"]}]